steam_exchange/__init__.py
steam_exchange/__main__.py
steam_exchange/main.py
steam_exchange/config/__init__.py
steam_exchange/config/config.py
steam_exchange/constants/__init__.py
steam_exchange/constants/apps.py
steam_exchange/constants/currency.py
steam_exchange/constants/fees.py
steam_exchange/engine/__init__.py
steam_exchange/engine/browser.py
steam_exchange/engine/engine.py
steam_exchange/engine/request.py
steam_exchange/engine/session.py
steam_exchange/market/__init__.py
steam_exchange/market/request.py
steam_exchange/market/response.py
steam_exchange-0.4.0.dist-info/LICENSE
steam_exchange-0.4.0.dist-info/METADATA
steam_exchange-0.4.0.dist-info/WHEEL
steam_exchange-0.4.0.dist-info/entry_points.txt
steam_exchange-0.4.0.dist-info/top_level.txt
steam_exchange-0.4.0.dist-info/RECORD
